<?xml version="1.0" encoding="utf-8" ?>
<Defs>

	<!-- ================== Projectiles ================== -->

  <ThingDef Class="CombatExtended.AmmoDef" Name="BaseCraftedPsionicLancer" ParentName="BaseBullet" Abstract="true">
    <graphicData>
      <texPath>Things/Projectile/PsionicBullet2</texPath>
      <graphicClass>Graphic_Single</graphicClass>
	  <shaderType>TransparentPostLight</shaderType>
      <drawSize>(3,3)</drawSize>
    </graphicData>
    <projectile>
      <damageDef>Psionic</damageDef>
      <speed>78</speed>
    </projectile>
  </ThingDef>

  <ThingDef Class="CombatExtended.AmmoDef" ParentName="BaseCraftedPsionicLancer">
    <defName>Bullet_CraftedPsionicLancer</defName>
    <label>psionic beam</label>
    <projectile Class="CombatExtended.ProjectilePropertiesCE">
      <damageAmountBase>18</damageAmountBase>
      <armorPenetrationBase>0.8</armorPenetrationBase>
    </projectile>
  </ThingDef>
	
</Defs>